emojicode/__init__.py
emojicode/core.py
emojicode-1.0.1.dist-info/METADATA
emojicode-1.0.1.dist-info/WHEEL
emojicode-1.0.1.dist-info/top_level.txt
emojicode-1.0.1.dist-info/RECORD
