Metadata-Version: 2.4
Name: emojicode
Version: 1.0.1
Summary: A fun emoji-based text encoder and decoder.
Author: Abbas
Author-email: your_email@example.com
Classifier: Programming Language :: Python :: 3
Classifier: License :: OSI Approved :: MIT License
Requires-Python: >=3.6
Dynamic: author
Dynamic: author-email
Dynamic: classifier
Dynamic: requires-python
Dynamic: summary
